WorldBrowser/__init__.py
WorldBrowser/movies/__init__.py
WorldBrowser/pictures/__init__.py
WorldBrowser/sounds/__init__.py
tests/__init__.py
WorldBrowser-2023.9.1.dist-info/LICENSE.txt
WorldBrowser-2023.9.1.dist-info/METADATA
WorldBrowser-2023.9.1.dist-info/WHEEL
WorldBrowser-2023.9.1.dist-info/top_level.txt
WorldBrowser-2023.9.1.dist-info/RECORD
