Metadata-Version: 2.1
Name: WorldBrowser
Version: 2023.9.1
Summary: A Browser that can browse the global interesting movies、pictures、news and so on。
Home-page: https://github.com/anzechannel/WorldBrowser
Author: anzechannel
Author-email: 348834851@qq.com
Classifier: Programming Language :: Python :: 3
Classifier: License :: OSI Approved :: MIT License
Classifier: Operating System :: OS Independent
Requires-Python: >=3.10
License-File: LICENSE.txt
